bengrn/VERSION
bengrn/__init__.py
bengrn/base.py
bengrn/tools/__init__.py
bengrn/tools/genie3.py
data/omnipath.parquet
data/tfchip_data.json
data/GroundTruth/BHLHE40.10.tsv
bengrn-1.3.0.dist-info/METADATA
bengrn-1.3.0.dist-info/WHEEL
bengrn-1.3.0.dist-info/licenses/LICENSE
bengrn-1.3.0.dist-info/RECORD
