Metadata-Version: 2.4
Name: benGRN
Version: 1.3.0
Summary: benchmarking gene regulatory networks
Project-URL: repository, https://github.com/jkobject/benGRN
Author-email: jeremie kalfon <jkobject@gmail.com>
License: MIT
License-File: LICENSE
Keywords: GRN,benchmark,comp bio,gene regulatory networks,scPRINT,scRNAseq
Requires-Python: >=3.10
Requires-Dist: anndata>=0.8.0
Requires-Dist: arboreto>=0.1.6
Requires-Dist: bionty>=0.49.0
Requires-Dist: ctxcore>=0.1.1
Requires-Dist: dask-expr>=1.0.0
Requires-Dist: decoupler>=1.2.0
Requires-Dist: gdown>=4.7.1
Requires-Dist: grnndata>=1.1.4
Requires-Dist: gseapy>=0.10.0
Requires-Dist: numba>=0.56.0
Requires-Dist: numpy>=1.21.0
Requires-Dist: omnipath>=1.0.0
Requires-Dist: pandas>=2.0.0
Requires-Dist: pyscenic>=0.12.0
Requires-Dist: rich>=13.5.0
Requires-Dist: scikit-learn>=1.0.0
Requires-Dist: scipy>=1.7.0
Requires-Dist: seaborn>=0.11.0
Requires-Dist: setuptools>=58.0.0
Provides-Extra: dev
Requires-Dist: coverage>=7.3.2; extra == 'dev'
Requires-Dist: gitchangelog>=3.0.4; extra == 'dev'
Requires-Dist: mkdocs-git-authors-plugin>=0.4.0; extra == 'dev'
Requires-Dist: mkdocs-git-revision-date-localized-plugin>=1.0.0; extra == 'dev'
Requires-Dist: mkdocs-jupyter>=0.2.0; extra == 'dev'
Requires-Dist: mkdocs>=1.5.3; extra == 'dev'
Requires-Dist: mkdocstrings-python>=0.10.0; extra == 'dev'
Requires-Dist: mkdocstrings>=0.22.0; extra == 'dev'
Requires-Dist: pytest-cov>=4.1.0; extra == 'dev'
Requires-Dist: pytest>=7.4.3; extra == 'dev'
Requires-Dist: ruff>=0.6.4; extra == 'dev'
